spatial_image_ngff.py
spatial_image_ngff-0.1.1.dist-info/LICENSE
spatial_image_ngff-0.1.1.dist-info/WHEEL
spatial_image_ngff-0.1.1.dist-info/METADATA
spatial_image_ngff-0.1.1.dist-info/RECORD
